LICENSE
MANIFEST.in
README.md
pyproject.toml
setup.py
TF_COMB.egg-info/PKG-INFO
TF_COMB.egg-info/SOURCES.txt
TF_COMB.egg-info/dependency_links.txt
TF_COMB.egg-info/not-zip-safe
TF_COMB.egg-info/requires.txt
TF_COMB.egg-info/top_level.txt
tfcomb/__init__.py
tfcomb/analysis.py
tfcomb/annotation.py
tfcomb/counting.pyx
tfcomb/logging.py
tfcomb/network.py
tfcomb/objects.py
tfcomb/plotting.py
tfcomb/utils.py
tfcomb/data/HOCOMOCOv11_HUMAN.txt
tfcomb/data/JASPAR2020_CORE_vertebrates.txt
tfcomb/data/dmelanogaster_genes.txt
tfcomb/data/drerio_genes.txt
tfcomb/data/hsapiens_genes.txt
tfcomb/data/mmusculus_genes.txt
tfcomb/data/scerevisiae_genes.txt
tfcomb/data/tax_ids.txt
tfcomb/data/xtropicalis_genes.txt