Metadata-Version: 2.4
Name: TF-COMB
Version: 1.1.1
Summary: Transcription Factor Co-Occurrence using Market Basket analysis
Home-page: 
Author: Mette Bentsen
Author-email: mette.bentsen@mpi-bn.mpg.de
License: MIT
Classifier: License :: OSI Approved :: MIT License
Classifier: Intended Audience :: Science/Research
Classifier: Topic :: Scientific/Engineering :: Bio-Informatics
Classifier: Programming Language :: Python :: 3
Requires-Python: >=3,
License-File: LICENSE
Requires-Dist: numpy
Requires-Dist: scipy
Requires-Dist: pysam
Requires-Dist: matplotlib>=2
Requires-Dist: pandas>=2.3.0
Requires-Dist: tobias>=0.11
Requires-Dist: networkx>=2.4
Requires-Dist: python-louvain
Requires-Dist: graphviz
Requires-Dist: statsmodels
Requires-Dist: goatools
Requires-Dist: uropa
Requires-Dist: qnorm
Requires-Dist: dill
Requires-Dist: seaborn
Requires-Dist: tqdm
Requires-Dist: IPython
Dynamic: author
Dynamic: author-email
Dynamic: classifier
Dynamic: description
Dynamic: description-content-type
Dynamic: license
Dynamic: license-file
Dynamic: requires-dist
Dynamic: requires-python
Dynamic: summary
